{
	"title": "Al ristorante cinese",
	"text": "Il proprietario di un ristorante cinese sotto casa tua ti ha preso in simpatia e spesso ti offre la cena. Ma ogni volta ti parla male degli italiani. Cosa fai?",
	"theme": "ristorante",
	"report": {
			"img":"idea.png",
			"text": "Rispetto a quanto si crede, la comunità cinese è meno chiusa e più ben disposta verso l'Italia, il cui nome si traduce letteralmente come “il Paese dove le grandi idee sono un profitto”",
			"source": "Ricerca ‘Analisi ed elaborazione dati sull’immigrazione cinese in Italia’ dell'OIM"	
		},
	"choices": [
		{
			"title": "Fingi di essere d'accordo",
			"button": "Fingi di essere d'accordo",
			"text": "Risparmi un po' di soldi ma rinunci a difendere il tuo paese.",
			"happiness": -50,
			"money": 30,
			"conseguence": {
				"type": "normal",
				"text": "Il trattamento di favore ti fa comodo, ma ti senti in colpa per essere stato zitto."
			}
		},
		{
			"title": "Smetti di andarci",
			"button": "Smetti di andarci",
			"text": "Qualche pasto gratis ti faceva comodo, ma la dignità non ha prezzo.",
			"happiness": 30,
			"money": 0,
			"conseguence": {
				"type": "normal",
				"text": "Hai dovuto rinunciare al trattamento di favore, ma almeno non dovrai più ascoltare discorsi che ti infastidiscono."
			}
		}
	]
}